ufoLib/__init__.py
ufoLib/converters.py
ufoLib/etree.py
ufoLib/filenames.py
ufoLib/glifLib.py
ufoLib/kerning.py
ufoLib/plistlib.py
ufoLib/pointPen.py
ufoLib/utils.py
ufoLib/validators.py
ufoLib/test/__init__.py
ufoLib/test/testSupport.py
ufoLib/test/test_GLIF1.py
ufoLib/test/test_GLIF2.py
ufoLib/test/test_UFO1.py
ufoLib/test/test_UFO2.py
ufoLib/test/test_UFO3.py
ufoLib/test/test_UFOConversion.py
ufoLib/test/test_etree.py
ufoLib/test/test_filenames.py
ufoLib/test/test_glifLib.py
ufoLib/test/test_plistlib.py
ufoLib/test/testdata/test.plist
ufoLib/test/testdata/DemoFont.ufo/fontinfo.plist
ufoLib/test/testdata/DemoFont.ufo/lib.plist
ufoLib/test/testdata/DemoFont.ufo/metainfo.plist
ufoLib/test/testdata/DemoFont.ufo/glyphs/A_.glif
ufoLib/test/testdata/DemoFont.ufo/glyphs/B_.glif
ufoLib/test/testdata/DemoFont.ufo/glyphs/F_.glif
ufoLib/test/testdata/DemoFont.ufo/glyphs/F__A__B_.glif
ufoLib/test/testdata/DemoFont.ufo/glyphs/G_.glif
ufoLib/test/testdata/DemoFont.ufo/glyphs/O_.glif
ufoLib/test/testdata/DemoFont.ufo/glyphs/R_.glif
ufoLib/test/testdata/DemoFont.ufo/glyphs/a.glif
ufoLib/test/testdata/DemoFont.ufo/glyphs/contents.plist
ufoLib/test/testdata/DemoFont.ufo/glyphs/testglyph1.glif
ufoLib/test/testdata/DemoFont.ufo/glyphs/testglyph1.reversed.glif
ufoLib/test/testdata/TestFont1 (UFO1).ufo/fontinfo.plist
ufoLib/test/testdata/TestFont1 (UFO1).ufo/groups.plist
ufoLib/test/testdata/TestFont1 (UFO1).ufo/kerning.plist
ufoLib/test/testdata/TestFont1 (UFO1).ufo/lib.plist
ufoLib/test/testdata/TestFont1 (UFO1).ufo/metainfo.plist
ufoLib/test/testdata/TestFont1 (UFO1).ufo/glyphs/A_.glif
ufoLib/test/testdata/TestFont1 (UFO1).ufo/glyphs/B_.glif
ufoLib/test/testdata/TestFont1 (UFO1).ufo/glyphs/contents.plist
ufoLib/test/testdata/TestFont1 (UFO2).ufo/features.fea
ufoLib/test/testdata/TestFont1 (UFO2).ufo/fontinfo.plist
ufoLib/test/testdata/TestFont1 (UFO2).ufo/groups.plist
ufoLib/test/testdata/TestFont1 (UFO2).ufo/kerning.plist
ufoLib/test/testdata/TestFont1 (UFO2).ufo/lib.plist
ufoLib-2.3.2.dist-info/LICENSE.txt
ufoLib-2.3.2.dist-info/METADATA
ufoLib-2.3.2.dist-info/WHEEL
ufoLib-2.3.2.dist-info/top_level.txt
ufoLib-2.3.2.dist-info/RECORD
