Metadata-Version: 2.1
Name: ufoLib
Version: 2.3.2
Summary: A low-level UFO reader and writer.
Home-page: https://github.com/unified-font-object/ufoLib
Author: Just van Rossum, Tal Leming, Erik van Blokland, others
Author-email: info@robofab.com
Maintainer: Just van Rossum, Tal Leming, Erik van Blokland
Maintainer-email: info@robofab.com
License: OpenSource, BSD-style
Platform: Any
Classifier: Development Status :: 4 - Beta
Classifier: Environment :: Console
Classifier: Environment :: Other Environment
Classifier: Intended Audience :: Developers
Classifier: Intended Audience :: End Users/Desktop
Classifier: License :: OSI Approved :: BSD License
Classifier: Natural Language :: English
Classifier: Operating System :: OS Independent
Classifier: Programming Language :: Python
Classifier: Topic :: Multimedia :: Graphics
Classifier: Topic :: Multimedia :: Graphics :: Graphics Conversion
Provides-Extra: lxml
Provides-Extra: testing
